pcgw_api-0.2.0.dist-info/METADATA
pcgw_api-0.2.0.dist-info/WHEEL
pcgw_api-0.2.0.dist-info/entry_points.txt
pcgw_api-0.2.0.dist-info/licenses/LICENSE
pcgw_api/__init__.py
pcgw_api/pcgw.py
pcgw_api/tables.json
pcgw_api/tables.py
pcgw_api/update_fields.py
pcgw_api/utils.py
pcgw_api-0.2.0.dist-info/RECORD
