Metadata-Version: 2.1
Name: pcgw_api
Version: 0.2.0
Summary: Client for the PCGamingWiki API
Author-Email: Idlusen <boulanger.m@mailoo.org>
License: LGPL-2.1
Requires-Python: >=3.13
Requires-Dist: httpx>=0.28.1
